leafagro/__init__.py
leafagro/agromonitoring.py
leafagro/common.py
leafagro/foliumap.py
leafagro/leafagro.py
leafagro/utils.py
leafagro-0.0.12.dist-info/LICENSE
leafagro-0.0.12.dist-info/METADATA
leafagro-0.0.12.dist-info/WHEEL
leafagro-0.0.12.dist-info/entry_points.txt
leafagro-0.0.12.dist-info/top_level.txt
leafagro-0.0.12.dist-info/RECORD
