Metadata-Version: 2.1
Name: leafagro
Version: 0.0.12
Summary: A Python Package for Analyzing Agriculture data obtained from Agromonitoring API.
Author-email: Haseeb Habeebulla <ibnhabeebulla@gmail.com>
License: MIT License
Project-URL: Homepage, https://github.com/Haseeb-oss-eng/leafagro
Keywords: leafagro
Classifier: Intended Audience :: Developers
Classifier: License :: OSI Approved :: MIT License
Classifier: Natural Language :: English
Classifier: Programming Language :: Python :: 3.8
Classifier: Programming Language :: Python :: 3.9
Classifier: Programming Language :: Python :: 3.10
Classifier: Programming Language :: Python :: 3.11
Classifier: Programming Language :: Python :: 3.12
Requires-Python: >=3.8
License-File: LICENSE
Requires-Dist: ipyleaflet
Requires-Dist: numpy
Requires-Dist: localtileserver
Requires-Dist: matplotlib
Requires-Dist: geopandas
Requires-Dist: pandas
Requires-Dist: ipywidgets
Requires-Dist: folium
Requires-Dist: pillow
Provides-Extra: all
Requires-Dist: leafagro[extra]; extra == "all"
Provides-Extra: extra
Requires-Dist: pandas; extra == "extra"
